squad/__init__.py
squad/_squad.py
squadco-1.0.1.dist-info/LICENSE
squadco-1.0.1.dist-info/METADATA
squadco-1.0.1.dist-info/WHEEL
squadco-1.0.1.dist-info/top_level.txt
squadco-1.0.1.dist-info/RECORD
