Metadata-Version: 2.1
Name: squadco
Version: 1.0.1
Summary: Python API Wrapper for Squadco.com Payment services
Home-page: https://github.com/joey1123455/squad-py.git
Author: Uche David, Joseph Folayan, Peter Adetunji
Author-email: debugtitan.hub@outlook.com, folayanjoey@gmail.com, peteradetunji30@gmail.com
License: MIT
Keywords: squadco payment gateway,squadco python package,squad
Classifier: Programming Language :: Python :: 3
Classifier: Programming Language :: Python :: 2
Classifier: License :: OSI Approved :: MIT License
Classifier: Operating System :: OS Independent
License-File: LICENSE
Requires-Dist: requests
